{"vehicle": {"Id": "v14", "x_coordinate": 207, "y_coordinate": 198, "radius": 23}, "Object": [{"Id": "o50", "x_coordinate": 220, "y_coordinate": 205, "timestamp": 13, "type": "person", "zone": "unsafe"}, {"Id": "o14", "x_coordinate": 107, "y_coordinate": 181, "timestamp": 29, "type": "obstruction", "zone": "unsafe"}, {"Id": "o17", "x_coordinate": -3, "y_coordinate": 150, "timestamp": 12, "type": "person", "zone": "unsafe"}, {"Id": "o4", "x_coordinate": 203, "y_coordinate": 139, "timestamp": 26, "type": "person", "zone": "safe"}, {"Id": "o26", "x_coordinate": 131, "y_coordinate": 165, "timestamp": 29, "type": "obstruction", "zone": "unsafe"}, {"Id": "o39", "x_coordinate": 60, "y_coordinate": 189, "timestamp": 27, "type": "person", "zone": "safe"}, {"Id": "o31", "x_coordinate": 9, "y_coordinate": 196, "timestamp": 16, "type": "person", "zone": "safe"}]}