{"vehicle": {"Id": "v19", "x_coordinate": 34, "y_coordinate": 197, "radius": 25}, "Object": [{"Id": "o28", "x_coordinate": 151, "y_coordinate": 150, "timestamp": 11, "type": "person", "zone": "unsafe"}, {"Id": "o9", "x_coordinate": 19, "y_coordinate": 158, "timestamp": 29, "type": "person", "zone": "safe"}, {"Id": "o33", "x_coordinate": 245, "y_coordinate": 162, "timestamp": 23, "type": "person", "zone": "unsafe"}, {"Id": "o21", "x_coordinate": 61, "y_coordinate": 137, "timestamp": 19, "type": "obstruction", "zone": "safe"}, {"Id": "o45", "x_coordinate": 208, "y_coordinate": 179, "timestamp": 13, "type": "obstruction", "zone": "unsafe"}]}